CHANGES.txt
DEPENDENCIES.txt
README.txt
bootstrap.py
buildout.cfg
setup.py
src/ks/__init__.py
src/ks.mailer.egg-info/PKG-INFO
src/ks.mailer.egg-info/SOURCES.txt
src/ks.mailer.egg-info/dependency_links.txt
src/ks.mailer.egg-info/namespace_packages.txt
src/ks.mailer.egg-info/not-zip-safe
src/ks.mailer.egg-info/requires.txt
src/ks.mailer.egg-info/top_level.txt
src/ks/mailer/__init__.py
src/ks/mailer/configure.zcml
src/ks/mailer/interfaces.py
src/ks/mailer/mailer.txt
src/ks/mailer/templateadapter.py
src/ks/mailer/vocabulary.py
src/ks/mailer/etc/ks.mailer-configure.zcml